rvcrunch/__init__.py
rvcrunch/__main__.py
rvcrunch-1.2.0.dist-info/METADATA
rvcrunch-1.2.0.dist-info/WHEEL
rvcrunch-1.2.0.dist-info/licenses/LICENSE
rvcrunch-1.2.0.dist-info/RECORD
