Metadata-Version: 2.1
Name: rvcrunch
Version: 1.2.0
Summary: RvTools Analysis Tool
Project-URL: Homepage, https://github.com/shapedthought/rvcrunchcli
Project-URL: Bug Tracker, https://github.com/shapedthought/rvcrunchcli/issues
Author-email: Ed Howard <exfhoward@protonmail.com>
License-File: LICENSE
Classifier: License :: OSI Approved :: MIT License
Classifier: Operating System :: OS Independent
Classifier: Programming Language :: Python :: 3
Requires-Python: >=3.10
Requires-Dist: numpy
Requires-Dist: pandas
